flexible_scorer/__init__.py
flexible_scorer/scorer.py
flexible_scorer/utils.py
flexible_scorer-0.1.14.dist-info/METADATA
flexible_scorer-0.1.14.dist-info/WHEEL
flexible_scorer-0.1.14.dist-info/top_level.txt
flexible_scorer-0.1.14.dist-info/RECORD
