Metadata-Version: 2.1
Name: flexible_scorer
Version: 0.1.14
Summary: A flexible scoring library using OpenAI models.
Author: Michael
Author-email: miryaboy@gmail.com
Classifier: Programming Language :: Python :: 3
Classifier: License :: OSI Approved :: MIT License
Classifier: Operating System :: OS Independent
Requires-Python: >=3.6
Requires-Dist: numpy
Requires-Dist: openai
Requires-Dist: plotly
Requires-Dist: scipy
